mrpy/__init__.py
mrpy/_utils.py
mrpy/base/__init__.py
mrpy/base/core.py
mrpy/base/special.py
mrpy/base/stats.py
mrpy/extra/__init__.py
mrpy/extra/analytic_model.py
mrpy/extra/likelihoods.py
mrpy/extra/physical_dependence.py
mrpy/extra/reparameterise.py
mrpy/fitting/__init__.py
mrpy/fitting/fit_curve.py
mrpy/fitting/fit_sample.py
mrpy-1.1.0.dist-info/DESCRIPTION.rst
mrpy-1.1.0.dist-info/METADATA
mrpy-1.1.0.dist-info/RECORD
mrpy-1.1.0.dist-info/WHEEL
mrpy-1.1.0.dist-info/metadata.json
mrpy-1.1.0.dist-info/top_level.txt
