Metadata-Version: 2.0
Name: mrpy
Version: 1.1.0
Summary: An efficient alternative halo mass function distribution
Home-page: https://github.com/steven-murray/mrpy
Author: Steven Murray
Author-email: steven.murray@curtin.edu.au
License: MIT
Keywords: halo mass function bayesian gamma
Platform: UNKNOWN
Classifier: Development Status :: 4 - Beta
Classifier: Programming Language :: Python :: 2
Classifier: Programming Language :: Python :: 2.7
Classifier: License :: OSI Approved :: MIT License
Classifier: Intended Audience :: Science/Research
Classifier: Natural Language :: English
Classifier: Topic :: Scientific/Engineering :: Mathematics
Classifier: Topic :: Scientific/Engineering :: Physics
Requires-Dist: cached-property
Requires-Dist: mpmath
Requires-Dist: numpy (>=1.6.2)
Requires-Dist: scipy (>=0.12.0)
